kurrentdbclient/__init__.py
kurrentdbclient/asyncio_client.py
kurrentdbclient/client.py
kurrentdbclient/common.py
kurrentdbclient/connection.py
kurrentdbclient/connection_spec.py
kurrentdbclient/events.py
kurrentdbclient/exceptions.py
kurrentdbclient/gossip.py
kurrentdbclient/instrumentation/__init__.py
kurrentdbclient/instrumentation/opentelemetry/__init__.py
kurrentdbclient/instrumentation/opentelemetry/attributes.py
kurrentdbclient/instrumentation/opentelemetry/grpc.py
kurrentdbclient/instrumentation/opentelemetry/package.py
kurrentdbclient/instrumentation/opentelemetry/spanners.py
kurrentdbclient/instrumentation/opentelemetry/utils.py
kurrentdbclient/instrumentation/opentelemetry/version.py
kurrentdbclient/persistent.py
kurrentdbclient/projections.py
kurrentdbclient/protos/google/rpc/code_pb2.py
kurrentdbclient/protos/google/rpc/code_pb2.pyi
kurrentdbclient/protos/google/rpc/code_pb2_grpc.py
kurrentdbclient/protos/kurrent/rpc/errors_pb2.py
kurrentdbclient/protos/kurrent/rpc/errors_pb2.pyi
kurrentdbclient/protos/kurrent/rpc/errors_pb2_grpc.py
kurrentdbclient/protos/kurrent/rpc/rpc_pb2.py
kurrentdbclient/protos/kurrent/rpc/rpc_pb2.pyi
kurrentdbclient/protos/kurrent/rpc/rpc_pb2_grpc.py
kurrentdbclient/protos/v1/cluster_pb2.py
kurrentdbclient/protos/v1/cluster_pb2.pyi
kurrentdbclient/protos/v1/cluster_pb2_grpc.py
kurrentdbclient/protos/v1/gossip_pb2.py
kurrentdbclient/protos/v1/gossip_pb2.pyi
kurrentdbclient/protos/v1/gossip_pb2_grpc.py
kurrentdbclient/protos/v1/persistent_pb2.py
kurrentdbclient/protos/v1/persistent_pb2.pyi
kurrentdbclient/protos/v1/persistent_pb2_grpc.py
kurrentdbclient/protos/v1/projections_pb2.py
kurrentdbclient/protos/v1/projections_pb2.pyi
kurrentdbclient/protos/v1/projections_pb2_grpc.py
kurrentdbclient/protos/v1/shared_pb2.py
kurrentdbclient/protos/v1/shared_pb2.pyi
kurrentdbclient/protos/v1/shared_pb2_grpc.py
kurrentdbclient/protos/v1/status_pb2.py
kurrentdbclient/protos/v1/status_pb2.pyi
kurrentdbclient/protos/v1/status_pb2_grpc.py
kurrentdbclient-1.2.dist-info/METADATA
kurrentdbclient-1.2.dist-info/WHEEL
kurrentdbclient-1.2.dist-info/licenses/LICENSE
kurrentdbclient-1.2.dist-info/RECORD
