Metadata-Version: 2.4
Name: kurrentdbclient
Version: 1.2
Summary: Python gRPC Client for KurrentDB
License: BSD-3-Clause
License-File: LICENSE
Author: John Bywater
Author-email: john.bywater@appropriatesoftware.net
Requires-Python: >=3.10
Classifier: Development Status :: 4 - Beta
Classifier: License :: OSI Approved :: BSD License
Classifier: Programming Language :: Python :: 3
Classifier: Programming Language :: Python :: 3.10
Classifier: Programming Language :: Python :: 3.11
Classifier: Programming Language :: Python :: 3.12
Classifier: Programming Language :: Python :: 3.13
Classifier: Programming Language :: Python :: 3.14
Classifier: Programming Language :: Python
Provides-Extra: opentelemetry
Requires-Dist: googleapis-common-protos
Requires-Dist: grpcio-status
Requires-Dist: grpcio[protobuf] (>=1.75.1,<2.0)
Requires-Dist: opentelemetry-api (>=1.28.0,<2.0) ; extra == "opentelemetry"
Requires-Dist: opentelemetry-instrumentation (>=0.49b0) ; extra == "opentelemetry"
Requires-Dist: opentelemetry-semantic-conventions (>=0.49b0) ; extra == "opentelemetry"
Requires-Dist: typing_extensions
Project-URL: Homepage, https://github.com/pyeventsourcing/kurrentdbclient
Project-URL: Repository, https://github.com/pyeventsourcing/kurrentdbclient
